gamesaver/__init__.py
gamesaver/__main__.py
gamesaver/config.py
gamesaver/output.py
gamesaver/src.py
gamesaver/util.py
gamesaver-1.0.0.dist-info/LICENSE.txt
gamesaver-1.0.0.dist-info/METADATA
gamesaver-1.0.0.dist-info/WHEEL
gamesaver-1.0.0.dist-info/dependency_links.txt
gamesaver-1.0.0.dist-info/entry_points.txt
gamesaver-1.0.0.dist-info/top_level.txt
gamesaver-1.0.0.dist-info/RECORD
