Metadata-Version: 2.1
Name: gamesaver
Version: 1.0.0
Summary: A simple cli tool for finding best deals on pc games
Home-page: https://github.com/michaelnavs/gamesaver
Author: Michael Navarro
Author-email: michaelnavs@gmail.com
License: MIT
Download-URL: https://github.com/michaelnavs/gamesaver/archive/1.0.0.tar.gz
Platform: UNKNOWN
Classifier: License :: OSI Approved :: MIT License
Classifier: Programming Language :: Python :: 3
Classifier: Programming Language :: Python :: 3.7
Requires-Python: >=3.7
Requires-Dist: certifi (==2021.5.30)
Requires-Dist: chardet (==4.0.0)
Requires-Dist: click (==8.0.1)
Requires-Dist: colorama (==0.4.4)
Requires-Dist: commonmark (==0.9.1)
Requires-Dist: idna (==2.10)
Requires-Dist: Pygments (==2.9.0)
Requires-Dist: requests (==2.25.1)
Requires-Dist: rich (==10.5.0)
Requires-Dist: urllib3 (==1.26.6)
